sugarpie/__init__.py
sugarpie/constants.py
sugarpie/helpers.py
sugarpie/pisugar.py
sugarpie-1.4.0.dist-info/LICENSE
sugarpie-1.4.0.dist-info/WHEEL
sugarpie-1.4.0.dist-info/METADATA
sugarpie-1.4.0.dist-info/RECORD
