Metadata-Version: 2.1
Name: sugarpie
Version: 1.4.0
Summary: SugarPie is a Python library to drive the PiSugar UPS / Battery.
Author-email: Bastien <b@kuma.la>
Classifier: License :: OSI Approved :: MIT License
Requires-Dist: smbus < 2
Project-URL: Home, https://gitlab.com/Bastien-BSF/sugarpie
